LICENSE
MANIFEST.in
README.md
requirements.txt
setup.cfg
setup.py
doge_datagen/__init__.py
doge_datagen/db_sink_factory.py
doge_datagen/doge.py
doge_datagen/kafka_avro_sink_factory.py
doge_datagen/kafka_sink_factory.py
doge_datagen/printing_sink.py
doge_datagen.egg-info/PKG-INFO
doge_datagen.egg-info/SOURCES.txt
doge_datagen.egg-info/dependency_links.txt
doge_datagen.egg-info/requires.txt
doge_datagen.egg-info/top_level.txt
examples/__init__.py
examples/doge_db_example.py
examples/doge_demo.py
examples/doge_example.py
examples/doge_example_common.py
examples/doge_kafka_avro_example.py
examples/doge_kafka_example.py
tests/__init__.py
tests/doge_datagen/__init__.py
tests/doge_datagen/test_db_sink.py
tests/doge_datagen/test_doge.py
tests/doge_datagen/test_kafka_avro_sink.py