Metadata-Version: 2.1
Name: doge-datagen
Version: 1.0.3
Summary: Data Online Generator
Home-page: https://github.com/getindata/doge-datagen
Author: GetInData
Author-email: office@getindata.com
License: Apache Software License (Apache 2.0)
Platform: UNKNOWN
Classifier: Programming Language :: Python :: 3.8
Classifier: Operating System :: OS Independent
Requires-Python: >=3.8
